cemir_error/__init__.py
cemir_error/ccerror.py
cemir_error/errors_de.py
cemir_error/errors_en.py
cemir_error/errors_fr.py
cemir_error/errors_tr.py
cemir_error/testet.py
cemir_error-202231003.3.3.dist-info/LICENSE
cemir_error-202231003.3.3.dist-info/METADATA
cemir_error-202231003.3.3.dist-info/WHEEL
cemir_error-202231003.3.3.dist-info/top_level.txt
cemir_error-202231003.3.3.dist-info/RECORD
